cflow_platform/__init__.py
cflow_platform/install_hooks.py
cflow_platform/public_api.py
cflow_platform/sdk.py
cflow_platform/verify_env.py
cflow_platform/assets/git-hooks/enhanced-post-commit
cflow_platform/assets/git-hooks/enhanced-pre-commit
cflow_platform/core/agent_loop.py
cflow_platform/core/direct_client.py
cflow_platform/core/handler_loader.py
cflow_platform/core/minimal_edit_applier.py
cflow_platform/core/public_api.py
cflow_platform/core/task_manager_adapter.py
cflow_platform/core/task_manager_client.py
cflow_platform/core/test_runner.py
cflow_platform/core/tool_registry.py
cflow_platform/core/web_mcp_server.py
cflow_platform/core/server/stdio.py
cflow_platform/handlers/enhanced_research_handlers.py
cflow_platform/handlers/linting_handlers.py
cflow_platform/handlers/plan_parser_handlers.py
cflow_platform/handlers/rag_handlers.py
cflow_platform/handlers/system_handlers.py
cflow_platform/handlers/task_handlers.py
cflow_platform/handlers/task_mod_handlers.py
cflow_platform/handlers/testing_handlers.py
cflow_platform/hooks/pre_commit_runner.py
cflow_platform/tests/test_contracts.py
cflow_platform/tests/test_testing_run_pytest.py
cflow_platform-0.1.6.dist-info/METADATA
cflow_platform-0.1.6.dist-info/WHEEL
cflow_platform-0.1.6.dist-info/entry_points.txt
cflow_platform-0.1.6.dist-info/licenses/LICENSE
cflow_platform-0.1.6.dist-info/RECORD
