Metadata-Version: 2.4
Name: cflow-platform
Version: 0.1.6
Summary: CFlow Platform (Phase 1 wrapper) for MCP public API, env verification, and hook installation
Author: Cerebral
License: MIT
License-File: LICENSE
Classifier: License :: OSI Approved :: MIT License
Classifier: Operating System :: OS Independent
Classifier: Programming Language :: Python :: 3
Classifier: Programming Language :: Python :: 3.11
Requires-Python: >=3.11
Requires-Dist: build>=1.3.0
Requires-Dist: httpx>=0.26.0
Requires-Dist: pytest>=8.0.0
Requires-Dist: twine>=6.1.0
